{"repo": {"timestamp": 1731815686000, "version": 20002, "name": "hydrapp Vanilla JS and Forms (Main) F-Droid Repo", "icon": "icon.png", "address": "https://pojntfx.github.io/hydrapp/hydrapp-example-vanillajs-forms/apk/main/repo", "description": "Android apps for hydrapp Vanilla JS and Forms (Main)."}, "requests": {"install": [], "uninstall": []}, "apps": [{"categories": ["dst"], "suggestedVersionCode": "2147483647", "license": "Unknown", "name": "hydrapp Vanilla JS and Forms (Main)", "added": 1731815686000, "icon": "com.pojtinger.felicitas.hydrapp.example.vanillajs.forms.main.1731811388.png", "packageName": "com.pojtinger.felicitas.hydrapp.example.vanillajs.forms.main", "lastUpdated": 1731815686000}], "packages": {"com.pojtinger.felicitas.hydrapp.example.vanillajs.forms.main": [{"added": 1731815686000, "apkName": "com.pojtinger.felicitas.hydrapp.example.vanillajs.forms.main.apk", "hash": "e9793944a9084a5f31a3fb8800ba09c750aebd58ae669aa4ace8be8d07319e71", "hashType": "sha256", "minSdkVersion": 8, "nativecode": ["$(uname -m)", "arm64-v8a", "armeabi", "armeabi-v7a", "x86"], "packageName": "com.pojtinger.felicitas.hydrapp.example.vanillajs.forms.main", "sig": "7ed2703bb2d4b35d8e066c0b61d08f22", "signer": "a7b7f933304901aca3e1b68b733c8eb761a108fe74916a4d2430665db46556b1", "size": 37164779, "targetSdkVersion": 34, "uses-permission": [["android.permission.INTERNET", null]], "versionCode": 1731811388, "versionName": "0.0.2-1731811388"}]}}